dext.py
dext-1.1.10.dist-info/METADATA
dext-1.1.10.dist-info/WHEEL
dext-1.1.10.dist-info/top_level.txt
dext-1.1.10.dist-info/RECORD
