Metadata-Version: 2.1
Name: dext
Version: 1.1.10
Summary: Dext is a tool to extract file dependencies from a code base. It is still under development.
Home-page: https://github.com/GabrieleMaurina/dext
Author: Gabriele Maurina
Author-email: gabrielemaurina95@gmail.com
License: MIT
Platform: UNKNOWN
Classifier: Programming Language :: Python :: 3
Classifier: License :: OSI Approved :: MIT License
Classifier: Operating System :: OS Independent
Requires-Python: >=3.8
